ndnGeometryCalc/__init__.py
ndnGeometryCalc/geoCalc.py
ndnGeometryCalc-0.0.1.dist-info/LICENSE
ndnGeometryCalc-0.0.1.dist-info/METADATA
ndnGeometryCalc-0.0.1.dist-info/WHEEL
ndnGeometryCalc-0.0.1.dist-info/top_level.txt
ndnGeometryCalc-0.0.1.dist-info/RECORD
