Metadata-Version: 2.1
Name: ndnGeometryCalc
Version: 0.0.1
Summary: This package calculates simple properties of geometric objects such as spheres, rectangular prisms, cylinders, and cones.
Author-email: Noah Zhou <nz2061@nyu.edu>, Daniel Pang <dp3228@nyu.edu>, Niket Gautam <ng2489@nyu.edu>
License: GNU GENERAL PUBLIC LICENSE
Project-URL: Homepage, https://github.com/software-students-spring2024/3-python-package-exercise-team-ndn
Keywords: python,package,build
Classifier: Programming Language :: Python :: 3
Classifier: Intended Audience :: Education
Classifier: License :: OSI Approved :: GNU General Public License v3 (GPLv3)
Classifier: Operating System :: OS Independent
Requires-Python: >=3.7
License-File: LICENSE
Provides-Extra: dev
Requires-Dist: pytest ; extra == 'dev'
